DingTouGaibianmingyun/README.md
DingTouGaibianmingyun/__init__.py
DingTouGaibianmingyun/__main__.py
DingTouGaibianmingyun/file.epub
DingTouGaibianmingyun/index.html
DingTouGaibianmingyun/css/__init__.py
DingTouGaibianmingyun/css/annotations.css
DingTouGaibianmingyun/css/main.css
DingTouGaibianmingyun/css/normalize.css
DingTouGaibianmingyun/css/popup.css
DingTouGaibianmingyun/font/__init__.py
DingTouGaibianmingyun/font/fontello.eot
DingTouGaibianmingyun/font/fontello.svg
DingTouGaibianmingyun/font/fontello.ttf
DingTouGaibianmingyun/font/fontello.woff
DingTouGaibianmingyun/img/__init__.py
DingTouGaibianmingyun/img/annotator-glyph-sprite.png
DingTouGaibianmingyun/img/annotator-icon-sprite.png
DingTouGaibianmingyun/img/apple-touch-icon.png
DingTouGaibianmingyun/img/cancelfullscreen.png
DingTouGaibianmingyun/img/close.png
DingTouGaibianmingyun/img/fullscreen.png
DingTouGaibianmingyun/img/loader.gif
DingTouGaibianmingyun/img/menu-icon.png
DingTouGaibianmingyun/img/save.png
DingTouGaibianmingyun/img/saved.png
DingTouGaibianmingyun/img/settings-s.png
DingTouGaibianmingyun/img/settings.png
DingTouGaibianmingyun/img/star.png
DingTouGaibianmingyun/js/__init__.py
DingTouGaibianmingyun/js/epub.js
DingTouGaibianmingyun/js/epub.min.js
DingTouGaibianmingyun/js/epub.min.map
DingTouGaibianmingyun/js/hooks.min.js
DingTouGaibianmingyun/js/hooks.min.map
DingTouGaibianmingyun/js/reader.js
DingTouGaibianmingyun/js/reader.js.map
DingTouGaibianmingyun/js/reader.min.js
DingTouGaibianmingyun/js/reader.min.map
DingTouGaibianmingyun/js/hooks/__init__.py
DingTouGaibianmingyun/js/hooks/extensions/__init__.py
DingTouGaibianmingyun/js/hooks/extensions/highlight.js
DingTouGaibianmingyun/js/libs/__init__.py
DingTouGaibianmingyun/js/libs/jquery.min.js
DingTouGaibianmingyun/js/libs/localforage.min.js
DingTouGaibianmingyun/js/libs/screenfull.js
DingTouGaibianmingyun/js/libs/screenfull.min.js
DingTouGaibianmingyun/js/libs/zip.min.js
DingTouGaibianmingyun/js/plugins/__init__.py
ding_tou_gaibianmingyun-2024.3.5.0.dist-info/METADATA
ding_tou_gaibianmingyun-2024.3.5.0.dist-info/WHEEL
ding_tou_gaibianmingyun-2024.3.5.0.dist-info/entry_points.txt
ding_tou_gaibianmingyun-2024.3.5.0.dist-info/top_level.txt
ding_tou_gaibianmingyun-2024.3.5.0.dist-info/RECORD
